fs/opener/youtubefs.py
fs/youtube/__init__.py
fs/youtube/youtubefs.py
fs.youtube-0.3.1.dist-info/LICENSE
fs.youtube-0.3.1.dist-info/METADATA
fs.youtube-0.3.1.dist-info/WHEEL
fs.youtube-0.3.1.dist-info/entry_points.txt
fs.youtube-0.3.1.dist-info/top_level.txt
fs.youtube-0.3.1.dist-info/zip-safe
fs.youtube-0.3.1.dist-info/RECORD
