Metadata-Version: 2.1
Name: fs.youtube
Version: 0.3.1
Summary: Youtube Filesystem for PyFilsystem2
Home-page: https://github.com/media-proxy/fs.youtube
Author: Merlin Kessler
Author-email: m3rlink@gmx.de
License: MIT
Keywords: filesystem,Pyfilesystem2,pafy,youtube
Platform: any
Classifier: Development Status :: 4 - Beta
Classifier: Intended Audience :: Developers
Classifier: License :: OSI Approved :: MIT License
Classifier: Operating System :: OS Independent
Classifier: Programming Language :: Python
Classifier: Programming Language :: Python :: 2.7
Classifier: Programming Language :: Python :: 3.5
Classifier: Programming Language :: Python :: 3.6
Classifier: Programming Language :: Python :: 3.7
Classifier: Topic :: Software Development :: Libraries :: Python Modules
Classifier: Topic :: System :: Filesystems
Requires-Python: !=3.0.*,!=3.1.*,!=3.2.*,!=3.3.*,!=3.4.*,>=2.7
Requires-Dist: fs (~=2.4.11)
Requires-Dist: pafy (~=0.5.4)
Requires-Dist: youtube-dl (>=2019.9.28)
Provides-Extra: dev
Requires-Dist: docutils (==0.15.2) ; extra == 'dev'
Requires-Dist: Pygments (==2.4.2) ; extra == 'dev'
Requires-Dist: codecov (==2.0.15) ; extra == 'dev'
Provides-Extra: test
Requires-Dist: green (==3.0.0) ; extra == 'test'
Requires-Dist: coverage (==4.5.4) ; extra == 'test'
Requires-Dist: mock (==3.0.5) ; (python_version < "3.3") and extra == 'test'
